tests/__init__.py
tests/test_project.py
wooey/__init__.py
wooey/admin.py
wooey/apps.py
wooey/django_compat.py
wooey/docs_settings.py
wooey/errors.py
wooey/settings.py
wooey/signals.py
wooey/tasks.py
wooey/test_settings.py
wooey/test_urls.py
wooey/urls.py
wooey/version.py
wooey/wooeystorage.py
wooey/backend/__init__.py
wooey/backend/command_line.py
wooey/backend/utils.py
wooey/conf/__init__.py
wooey/conf/project_template/__init__.py
wooey/conf/project_template/middleware.py
wooey/conf/project_template/requirements.txt
wooey/conf/project_template/wooey_celery_app.py
wooey/conf/project_template/settings/__init__.py
wooey/conf/project_template/settings/user_settings.py
wooey/conf/project_template/settings/wooey_settings.py
wooey/conf/project_template/urls/__init__.py
wooey/conf/project_template/urls/user_urls.py
wooey/conf/project_template/urls/wooey_urls.py
wooey/forms/__init__.py
wooey/forms/config.py
wooey/forms/factory.py
wooey/forms/fields.py
wooey/forms/scripts.py
wooey/locale/de/LC_MESSAGES/django.mo
wooey/locale/de/LC_MESSAGES/django.po
wooey/locale/fr/LC_MESSAGES/django.mo
wooey/locale/fr/LC_MESSAGES/django.po
wooey/locale/ja/LC_MESSAGES/django.mo
wooey/locale/ja/LC_MESSAGES/django.po
wooey/locale/ko/LC_MESSAGES/django.mo
wooey/locale/ko/LC_MESSAGES/django.po
wooey/locale/nl/LC_MESSAGES/django.mo
wooey/locale/nl/LC_MESSAGES/django.po
wooey/locale/zh_Hans/LC_MESSAGES/django.mo
wooey/locale/zh_Hans/LC_MESSAGES/django.po
wooey/management/__init__.py
wooey/management/commands/__init__.py
wooey/management/commands/addscript.py
wooey/migrations/0001_initial.py
wooey/migrations/0002_remove_scriptparameter_output_path.py
wooey/migrations/0003_populate_from_slug.py
wooey/migrations/0004_choice_limits.py
wooey/migrations/0005_size_bytes.py
wooey/migrations/0006_script_group_defaults.py
wooey/migrations/0007_script_documentation.py
wooey/migrations/0008_short_param_admin.py
wooey-0.11.1.dist-info/METADATA
wooey-0.11.1.dist-info/RECORD
wooey-0.11.1.dist-info/WHEEL
wooey-0.11.1.dist-info/entry_points.txt
wooey-0.11.1.dist-info/top_level.txt
