Metadata-Version: 2.1
Name: wooey
Version: 0.11.1
Summary: A Django app which creates a web GUI and task interface for argparse scripts
Home-page: http://www.github.com/wooey/wooey
Author: Chris Mitchell <chris.mit7@gmail.com>, Martin Fitzpatrick <martin.fitzpatrick@gmail.com>
Author-email: UNKNOWN
License: UNKNOWN
Platform: UNKNOWN
Classifier: Environment :: Web Environment
Classifier: Framework :: Django
Classifier: Intended Audience :: Developers
Classifier: License :: OSI Approved :: BSD License
Classifier: Operating System :: OS Independent
Classifier: Programming Language :: Python
Classifier: Programming Language :: Python :: 2.7
Classifier: Programming Language :: Python :: 3
Classifier: Programming Language :: Python :: 3.3
Classifier: Programming Language :: Python :: 3.4
Classifier: Topic :: Internet :: WWW/HTTP
Classifier: Topic :: Internet :: WWW/HTTP :: Dynamic Content
Requires-Dist: celery (<5,>=4.0)
Requires-Dist: clinto (>=0.3.0)
Requires-Dist: Django (<2.2,>=1.11)
Requires-Dist: django-autoslug
Requires-Dist: django-celery-results
Requires-Dist: jsonfield
Requires-Dist: six
Requires-Dist: eventlet (>=0.22.1); platform_system == "Windows"
Requires-Dist: pypiwin32 (==219); platform_system == "Windows" and python_version == "3.4"
Requires-Dist: pypiwin32; platform_system == "Windows" and python_version > "3.4"
